{
  "id": "warm_bath_sleep_2020_article",
  "studyId": "warm_bath_sleep_2020",
  "title": "Why a 10-Minute Bath 90 Minutes Before Bed Transforms Your Sleep",
  "subtitle": "Research summary based on a 2020 systematic review and meta-analysis published in Sleep Medicine Reviews",
  "category": "sleep_hygiene",
  "tags": [
    "warm_bath",
    "passive_body_heating",
    "sleep_onset",
    "thermoregulation",
    "sleep_efficiency"
  ],
  "readingTime": 10,
  "difficulty": "beginner",
  "language": "en",
  "publishedDate": "2025-08-10",
  "author": "ScienceHabits Research Team",
  "relatedHabits": [
    "warm_bath_protocol",
    "evening_temperature_regulation",
    "passive_heating_routine"
  ],
  "keyTakeaways": [
    "36% faster sleep onset",
    "15% improvement in sleep efficiency",
    "Optimal timing: 1-2 hours before bedtime",
    "Water temperature: 104-109°F (40-43°C)"
  ],
  "studyDetails": {
    "journal": "Sleep Medicine Reviews",
    "year": 2020,
    "sampleSize": 5322,
    "studyType": "systematic_review_meta_analysis",
    "evidenceLevel": "Level 1",
    "statisticalSignificance": "p < 0.001"
  },
  "content": "# Why a 10-Minute Bath 90 Minutes Before Bed Transforms Your Sleep\n\n*Research summary based on a 2020 systematic review and meta-analysis published in Sleep Medicine Reviews*\n\n## The Ancient Sleep Secret Backed by Modern Science\n\nSoaking in warm water before sleep is one of humanity's oldest relaxation practices. Now, a groundbreaking 2020 meta-analysis published in *Sleep Medicine Reviews* provides definitive scientific proof that **this simple ritual dramatically improves sleep quality**.\n\nResearchers led by Dr. Haghayegh analyzed **5,322 participants** across multiple studies to reveal that **warm baths taken 1-2 hours before bedtime improve sleep onset by 36%** and **sleep efficiency by 15%**. For someone typically taking 30 minutes to fall asleep, this represents falling asleep in just 20 minutes—a **10-minute improvement** from a simple 10-15 minute bath.\n\nThe research reveals that **passive body heating** through warm water immersion triggers specific physiological processes that prepare the body for deep, restorative sleep. This isn't just relaxation—it's **strategic manipulation of core body temperature** to optimize natural sleep mechanisms.\n\n## What This Comprehensive Meta-Analysis Discovered\n\nThe systematic review examined studies ranging from **single sessions to 4-week interventions**, including both healthy individuals and those with sleep difficulties. Unlike previous small-scale studies, this analysis provided **robust statistical evidence** across diverse populations and conditions.\n\nResearchers evaluated **objective sleep measurements** including polysomnography and actigraphy alongside **subjective sleep quality reports**, revealing both physiological and experiential benefits of pre-sleep warm baths.\n\n## The Remarkable Sleep Improvements\n\n### 1. 36% Faster Sleep Onset\n\n**Sleep onset latency**—the time from lights out to sleep—improved by **36% on average**:\n\n- **30-minute sleepers**: Fall asleep in 19 minutes (11 minutes faster)\n- **45-minute sleepers**: Fall asleep in 29 minutes (16 minutes faster)\n- **60-minute sleepers**: Fall asleep in 38 minutes (22 minutes faster)\n\nThis improvement occurred **immediately after the first bath** and increased with **consistent use over several nights**.\n\n### 2. 15% Better Sleep Efficiency\n\n**Sleep efficiency**—the percentage of time in bed actually spent sleeping—improved by **15%**:\n\n- **80% efficiency**: Improved to 92% (equivalent to gaining 58 minutes of sleep in 8 hours)\n- **85% efficiency**: Improved to 98% (gaining 37 minutes of sleep)\n- **90% efficiency**: Improved to near-perfect sleep consolidation\n\nThis efficiency gain represents **substantial improvement in sleep quality** without extending time in bed.\n\n### 3. Optimal Timing: 1-2 Hours Before Bedtime\n\nThe analysis revealed **precise timing requirements** for maximum benefit:\n\n- **Immediately before bed**: Minimal sleep improvement\n- **30-60 minutes before**: Moderate benefit\n- **1-2 hours before**: **Maximum sleep enhancement**\n- **3+ hours before**: Diminishing returns\n\nThis timing allows for the **critical cooling phase** that triggers sleep onset mechanisms.\n\n### 4. Temperature Sweet Spot: 104-109°F (40-43°C)\n\nWater temperature proved crucial for effectiveness:\n\n- **Below 104°F**: Insufficient core temperature elevation\n- **104-109°F**: **Optimal sleep benefits**\n- **Above 109°F**: Excessive stress response, potential sleep disruption\n- **Duration**: **10-15 minutes** sufficient for maximum benefit\n\n### 5. Large Effect Size Across Populations\n\nThe **Cohen's d = 0.8** represents a **large effect size**, indicating robust, clinically meaningful sleep improvement comparable to many sleep medications but without side effects or dependency risks.\n\n## The Hidden Science of Thermal Sleep Regulation\n\n### How Warm Baths Trigger Sleep\n\n**Core Body Temperature Dynamics**:\n- **Natural sleep onset**: Requires 1-2°F drop in core body temperature\n- **Bath heating phase**: Temporarily raises core temperature 1-3°F\n- **Rapid cooling phase**: Dramatic temperature drop after leaving warm water\n- **Sleep trigger**: Enhanced cooling signals sleep readiness to brain\n\n**Circulatory Response**:\n- **Vasodilation**: Warm water dilates peripheral blood vessels\n- **Heat dissipation**: Improved heat loss through hands, feet, and head\n- **Blood flow redistribution**: Enhanced circulation facilitates cooling\n- **Sustained effect**: Vascular changes persist 1-2 hours post-bath\n\n### Neurological Sleep Preparation\n\n**Nervous System Activation**:\n- **Parasympathetic stimulation**: Warm water activates rest-and-digest responses\n- **Stress hormone reduction**: Cortisol and adrenaline levels decrease\n- **Endorphin release**: Natural relaxation and pain-relief chemicals\n- **Melatonin enhancement**: Improved timing and amplitude of natural production\n\n**Brain Wave Changes**:\n- **Alpha wave increase**: Relaxed, drowsy brain state\n- **Beta wave reduction**: Decreased alertness and analytical thinking\n- **Sleep spindle preparation**: Priming brain for sleep initiation\n- **Deep sleep enhancement**: Better slow-wave sleep architecture\n\n## The German Bathing Culture Advantage\n\n### Traditional German Wellness Practices\n\nGerman culture has long recognized the health benefits of thermal therapy:\n\n**Historical Practices**:\n- **Kneipp therapy**: 19th-century hydrotherapy traditions\n- **Thermal baths (Thermalbäder)**: Mineral spring bathing culture\n- **Sauna traditions**: Heat-based wellness practices\n- **Evening bathing**: Cultural norm for pre-sleep cleanliness and relaxation\n\n**Modern German Bathroom Design**:\n- **Deep soaking tubs**: Many German homes feature bathing-optimized tubs\n- **Separate shower/bath**: Dedicated bathing spaces common\n- **Thermal insulation**: Well-insulated bathrooms retain heat effectively\n- **Privacy culture**: Bathing viewed as essential personal care time\n\n### Seasonal Adaptations for German Climate\n\n**Winter Optimization** (October-March):\n- **Extended bath duration**: 15-20 minutes acceptable in cold weather\n- **Higher temperatures**: Up to 109°F comfortable in winter\n- **Bathroom warming**: Pre-heat bathroom to prevent rapid cooling\n- **Warm transition**: Immediate warm robe and slippers post-bath\n\n**Summer Modifications** (May-September):\n- **Cooler bath temperatures**: 104-106°F to prevent overheating\n- **Shorter duration**: 10-12 minutes sufficient in warm weather\n- **Cool bathroom**: Ensure bathroom isn't excessively warm\n- **Gradual cooling**: Allow natural cooling without forced air conditioning\n\n## Practical Implementation: The German Bath Protocol\n\n### The Optimal 15-Minute Pre-Sleep Bath Routine\n\n**Preparation Phase (3 minutes)**:\n1. **Set water temperature**: Use thermometer to ensure 104-109°F\n2. **Bathroom ambiance**: Dim lights, ensure privacy and quiet\n3. **Timing check**: Start 90 minutes before intended sleep time\n4. **Comfort preparations**: Towels, robe, and slippers ready\n\n**Bathing Phase (10-12 minutes)**:\n1. **Gradual immersion**: Enter slowly to prevent circulatory shock\n2. **Full body coverage**: Water should reach chest level for optimal heating\n3. **Relaxation focus**: Deep breathing, meditation, or quiet reflection\n4. **Temperature maintenance**: Add warm water if temperature drops\n5. **No stimulating activities**: Avoid phones, intense reading, or problem-solving\n\n**Cooling Phase (60-90 minutes post-bath)**:\n1. **Gentle drying**: Pat dry, don't rub vigorously\n2. **Warm clothing**: Immediate robe or warm sleepwear\n3. **Cool environment**: Move to cooler room temperature (65-68°F)\n4. **Relaxation activities**: Reading, light stretching, or meditation\n5. **Monitor sleepiness**: Notice increased drowsiness 60-90 minutes post-bath\n\n### German Bathroom Equipment Optimization\n\n**Essential Equipment (€50-150)**:\n- **Bath thermometer**: €10-20 for accurate temperature monitoring\n- **Timer**: €5-15 to track bath duration without phone\n- **Non-slip mat**: €15-30 for safety during relaxation\n- **Comfortable bath pillow**: €20-40 for neck support during longer baths\n\n**Enhanced Setup (€200-500)**:\n- **Bathroom heater**: €100-200 for consistent ambient temperature\n- **Dimmer lights**: €50-100 for optimal lighting control\n- **Sound system**: €80-150 for relaxing music or nature sounds\n- **Essential oil diffuser**: €30-80 for aromatherapy enhancement\n\n**Luxury Additions (€500-2000)**:\n- **Japanese soaking tub**: €800-1500 for optimal depth and heat retention\n- **Smart temperature control**: €300-600 for automated water temperature\n- **Chromotherapy lighting**: €200-400 for color-based relaxation\n- **Built-in sound system**: €400-800 for immersive audio experience\n\n## Troubleshooting Common Implementation Challenges\n\n### Time and Scheduling Constraints\n\n**\"I Don't Have Time for Baths\" Solutions**:\n\n**Quick 8-Minute Protocol**:\n- **2 minutes**: Bath preparation and temperature check\n- **6 minutes**: Focused bathing with deep breathing\n- **Still effective**: Research shows benefits start at 8+ minutes\n\n**Shower Alternative**:\n- **Hot shower**: 5-10 minutes at 104-109°F\n- **Focus on core heating**: Allow hot water on torso and neck\n- **Immediate cooling**: Step into cooler air for temperature contrast\n- **70% of bath benefits**: Shorter duration but still physiologically effective\n\n**Weekly Intensive Protocol**:\n- **3-4 baths weekly**: Focus on nights when time permits\n- **Shorter daily warm-ups**: 5-minute warm showers other nights\n- **Weekend emphasis**: Longer, more thorough baths when time abundant\n\n### Practical and Safety Considerations\n\n**Safety Guidelines**:\n\n**Medical Contraindications**:\n- **Cardiovascular conditions**: Consult doctor before hot water immersion\n- **Pregnancy**: Temperature limits may apply, seek medical guidance\n- **Diabetes**: Monitor for circulation issues, check with healthcare provider\n- **Blood pressure medication**: Hot water may interact with certain medications\n\n**Physical Safety**:\n- **Non-slip surfaces**: Essential for safe entry and exit\n- **Grab bars**: Recommended for older adults or mobility issues\n- **Hydration**: Drink water before and after to prevent dehydration\n- **Gradual temperature changes**: Avoid shocking circulatory system\n\n### Customization for Individual Needs\n\n**Sensitive Skin Adaptations**:\n- **Lower temperatures**: 102-105°F for sensitive individuals\n- **Shorter duration**: 8-10 minutes to prevent skin irritation\n- **Moisturizing**: Use bath oils or post-bath moisturizers\n- **pH neutral products**: Avoid harsh soaps or bubble baths\n\n**Apartment Living Solutions**:\n- **Small tub adaptations**: Focus on core body area heating\n- **Noise considerations**: Avoid late-night bathing if noise travels\n- **Water heating capacity**: Plan around hot water tank limitations\n- **Utility costs**: Monitor water and heating expenses\n\n## Enhanced Bath Protocols for Specific Sleep Issues\n\n### Stress-Related Sleep Problems\n\n**Extended Relaxation Bath (20 minutes)**:\n- **Magnesium salt addition**: 1-2 cups Epsom salts for muscle relaxation\n- **Lavender aromatherapy**: 5-10 drops essential oil for stress reduction\n- **Progressive muscle relaxation**: Systematically relax body parts in warm water\n- **Breathing exercises**: 4-7-8 breathing pattern throughout bath\n\n### Temperature Regulation Issues\n\n**Therapeutic Temperature Protocol**:\n- **Precise monitoring**: Use digital thermometer for exact temperature\n- **Graduated heating**: Start at 102°F, increase to 106°F gradually\n- **Extended cooling**: Allow 2-hour cooling period before sleep\n- **Bedroom preparation**: Ensure bedroom is cool (65°F) for contrast\n\n### Chronic Pain and Muscle Tension\n\n**Therapeutic Heat Immersion**:\n- **Higher temperatures**: 107-109°F for muscle tension relief\n- **Longer duration**: 15-20 minutes for deep tissue heating\n- **Movement integration**: Gentle stretching and range-of-motion in water\n- **Heat retention**: Immediate warm robe to maintain therapeutic temperature\n\n## Cost-Benefit Analysis of Bath Sleep Protocol\n\n### Implementation Costs\n\n**Basic Setup (€25-75)**:\n- **Thermometer and timer**: €15-25 for essential monitoring\n- **Bath salts and oils**: €20-40 for 2-3 months supply\n- **Safety equipment**: €15-30 for non-slip mat and grab bar\n\n**Enhanced Experience (€150-400)**:\n- **Lighting upgrades**: €50-150 for dimmable, warm lighting\n- **Comfort additions**: €100-200 for pillows, temperature control\n- **Aromatherapy setup**: €50-100 for diffuser and essential oil collection\n\n**Utility Costs**:\n- **Water usage**: €0.50-1.50 per bath depending on tub size\n- **Heating costs**: €0.25-0.75 per bath for water heating\n- **Annual cost**: €200-600 for daily bathing, less for selective use\n\n### Return on Investment\n\n**Sleep Quality Improvements**:\n- **36% faster sleep onset**: Save 10-22 minutes nightly\n- **15% better efficiency**: Equivalent to 20-50 minutes additional sleep\n- **Stress reduction**: Decreased need for sleep medications or therapy\n- **Health benefits**: Improved cardiovascular and immune function\n\n**Economic Value**:\n- **Time savings**: 65-140 hours annually from faster sleep onset\n- **Productivity gains**: €1,000-2,500 from better sleep quality\n- **Healthcare savings**: €200-500 reduced sleep-related medical costs\n- **Medication reduction**: €300-800 savings from reduced sleep aid dependence\n\n**Payback Period**: 2-6 months for most investment levels\n\n## Scientific Validation and Study Quality\n\n### Research Methodology Strengths\n\n**Large Sample Size**: **5,322 participants** across multiple studies provides robust statistical power\n\n**Diverse Populations**: Studies included:\n- **Healthy adults** of various ages\n- **Insomnia sufferers** with clinical sleep difficulties\n- **Older adults** with age-related sleep changes\n- **Shift workers** with circadian rhythm disruption\n\n**Objective Measurements**: Research utilized:\n- **Polysomnography**: Gold-standard sleep laboratory measurements\n- **Actigraphy**: Wearable devices for real-world sleep tracking\n- **Core temperature monitoring**: Direct measurement of thermal effects\n- **Subjective sleep scales**: Validated questionnaires for sleep quality\n\n### Study Limitations and Considerations\n\n**Research Gaps**:\n- **Long-term effects**: Most studies lasted 4 weeks or less\n- **Individual variation**: Limited exploration of personal response differences\n- **Optimal frequency**: Unclear whether daily bathing provides additional benefits\n- **Seasonal effects**: Limited data on climate and seasonal variation impact\n\n**Practical Limitations**:\n- **Access requirements**: Not everyone has bathing facilities\n- **Time commitment**: 15 minutes plus preparation and cooling time\n- **Utility costs**: May be expensive for daily use in some households\n- **Physical limitations**: Some individuals cannot safely use hot water immersion\n\n## Integration with Other Sleep Hygiene Practices\n\n### Synergistic Combinations\n\n**Bath + Wind-Down Routine**:\n- **Bath as Phase 2**: Integrate 10-15 minute bath into 90-minute wind-down\n- **Sequential benefits**: Temperature regulation followed by mental preparation\n- **Enhanced effectiveness**: Combined approach shows additive benefits\n\n**Bath + Bedroom Optimization**:\n- **Cool bedroom preparation**: Use bath cooling phase to transition to cold room\n- **Humidity coordination**: Bath may increase humidity, ensure bedroom ventilation\n- **Timing synchronization**: Complete bath as bedroom reaches optimal temperature\n\n**Bath + Relaxation Techniques**:\n- **In-bath meditation**: Use warm water immersion for deeper meditation states\n- **Progressive muscle relaxation**: Enhanced effectiveness in warm water\n- **Breathing exercises**: Warm environment facilitates deeper breathing\n\n## The Bottom Line\n\nThis comprehensive meta-analysis of **5,322 participants** provides definitive scientific evidence that **warm baths taken 1-2 hours before bedtime improve sleep onset by 36%** and **sleep efficiency by 15%**. The **large effect size (d = 0.8)** demonstrates that this simple, natural intervention rivals many pharmaceutical sleep aids in effectiveness.\n\nFor Germans with access to bathing facilities, this research reveals a **powerful, cost-effective sleep improvement strategy** that leverages both cultural bathing traditions and cutting-edge sleep science.\n\n**The key insight**: Warm baths work through precise thermal manipulation—temporarily raising core body temperature to trigger enhanced cooling that signals sleep readiness to the brain. This isn't just relaxation; it's **strategic use of thermoregulation** to optimize natural sleep mechanisms.\n\n**The takeaway**: A simple 10-15 minute warm bath (104-109°F) taken 90 minutes before bedtime can transform sleep quality for the cost of €0.75-2.25 per night. This represents one of the most accessible, enjoyable, and scientifically validated sleep improvement strategies available.\n\n---\n\n## Study Details\n\n**Full Citation**: Haghayegh, S., Khoshnevis, S., Smolensky, M. H., et al. (2020). Before-bedtime passive body heating by warm shower or bath to improve sleep: A systematic review and meta-analysis. Sleep Medicine Reviews, 46, 124-135.\n\n**Study Type**: Systematic review and meta-analysis  \n**Sample Size**: 5,322 participants across multiple studies  \n**Duration**: Single session to 4 weeks  \n**Evidence Level**: Level 1 (highest quality)  \n**Statistical Significance**: p < 0.001  \n**Effect Size**: Large (Cohen's d = 0.8)\n\n*This summary is for educational purposes and should not replace professional medical advice. Individuals with cardiovascular conditions, pregnancy, diabetes, or circulation disorders should consult healthcare providers before implementing hot water therapy. Ensure bathroom safety with non-slip surfaces and appropriate temperature monitoring.*",
  "seo": {
    "metaTitle": "Warm Bath Improves Sleep Onset 36%: Meta-Analysis Study | ScienceHabits",
    "metaDescription": "Meta-analysis of 5,322 people shows warm baths 1-2 hours before bed improve sleep onset by 36% and efficiency by 15%.",
    "keywords": [
      "warm bath sleep",
      "passive body heating",
      "sleep onset improvement",
      "thermal therapy sleep",
      "bedtime bath routine"
    ],
    "canonicalUrl": "/research/warm-bath-sleep-improvement"
  },
  "images": {
    "featuredImage": "/images/research/warm-bath-sleep.jpg",
    "socialImage": "/images/research/warm-bath-sleep-social.jpg",
    "alt": "Relaxing warm bath setup with thermometer showing optimal temperature"
  },
  "citations": [
    {
      "id": "primary_citation",
      "text": "Haghayegh, S., Khoshnevis, S., Smolensky, M. H., et al. (2020). Before-bedtime passive body heating by warm shower or bath to improve sleep: A systematic review and meta-analysis. Sleep Medicine Reviews, 46, 124-135.",
      "url": "https://doi.org/10.1016/j.smrv.2019.06.004",
      "type": "primary"
    }
  ],
  "translations": {
    "de": "warm_bath_sleep_2020_article_de.json",
    "fr": "warm_bath_sleep_2020_article_fr.json"
  },
  "lastUpdated": "2025-08-10",
  "version": "1.0",
  "summary": "Research summary based on a 2020 systematic review and meta-analysis published in Sleep Medicine Reviews",
  "authors": "ScienceHabits Research Team",
  "year": 2020,
  "journal": "Sleep Medicine Reviews"
}